[{"__symbolic":"module","version":4,"metadata":{"DatatableComponent":{"__symbolic":"class","decorators":[{"__symbolic":"call","expression":{"__symbolic":"reference","module":"@angular/core","name":"Component","line":25,"character":1},"arguments":[{"selector":"ngx-datatable","template":"\n    <div\n      visibilityObserver\n      (visible)=\"recalculate()\">\n      <datatable-header\n        *ngIf=\"headerHeight\"\n        [sorts]=\"sorts\"\n        [sortType]=\"sortType\"\n        [scrollbarH]=\"scrollbarH\"\n        [innerWidth]=\"_innerWidth\"\n        [offsetX]=\"_offsetX | async\"\n        [dealsWithGroup]=\"groupedRows\"\n        [columns]=\"_internalColumns\"\n        [headerHeight]=\"headerHeight\"\n        [reorderable]=\"reorderable\"\n        [targetMarkerTemplate]=\"targetMarkerTemplate\"\n        [sortAscendingIcon]=\"cssClasses.sortAscending\"\n        [sortDescendingIcon]=\"cssClasses.sortDescending\"\n        [allRowsSelected]=\"allRowsSelected\"\n        [selectionType]=\"selectionType\"\n        (sort)=\"onColumnSort($event)\"\n        (resize)=\"onColumnResize($event)\"\n        (reorder)=\"onColumnReorder($event)\"\n        (select)=\"onHeaderSelect($event)\"\n        (columnContextmenu)=\"onColumnContextmenu($event)\">\n      </datatable-header>\n      <datatable-body\n        [groupRowsBy]=\"groupRowsBy\"\n        [groupedRows]=\"groupedRows\"\n        [rows]=\"_internalRows\"\n        [groupExpansionDefault]=\"groupExpansionDefault\"\n        [scrollbarV]=\"scrollbarV\"\n        [scrollbarH]=\"scrollbarH\"\n        [virtualization]=\"virtualization\"\n        [loadingIndicator]=\"loadingIndicator\"\n        [externalPaging]=\"externalPaging\"\n        [rowHeight]=\"rowHeight\"\n        [rowCount]=\"rowCount\"\n        [offset]=\"offset\"\n        [trackByProp]=\"trackByProp\"\n        [columns]=\"_internalColumns\"\n        [pageSize]=\"pageSize\"\n        [offsetX]=\"_offsetX | async\"\n        [rowDetail]=\"rowDetail\"\n        [groupHeader]=\"groupHeader\"\n        [selected]=\"selected\"\n        [innerWidth]=\"_innerWidth\"\n        [bodyHeight]=\"bodyHeight\"\n        [selectionType]=\"selectionType\"\n        [emptyMessage]=\"messages.emptyMessage\"\n        [rowIdentity]=\"rowIdentity\"\n        [rowClass]=\"rowClass\"\n        [selectCheck]=\"selectCheck\"\n        [displayCheck]=\"displayCheck\"\n        [summaryRow]=\"summaryRow\"\n        [summaryHeight]=\"summaryHeight\"\n        [summaryPosition]=\"summaryPosition\"\n        (page)=\"onBodyPage($event)\"\n        (activate)=\"activate.emit($event)\"\n        (rowContextmenu)=\"onRowContextmenu($event)\"\n        (select)=\"onBodySelect($event)\"\n        (scroll)=\"onBodyScroll($event)\"\n        (treeAction)=\"onTreeAction($event)\">\n      </datatable-body>\n      <datatable-footer\n        *ngIf=\"footerHeight\"\n        [rowCount]=\"rowCount\"\n        [pageSize]=\"pageSize\"\n        [offset]=\"offset\"\n        [limitOptions]=\"limitOptions\"\n        [footerHeight]=\"footerHeight\"\n        [footerTemplate]=\"footer\"\n        [totalMessage]=\"messages.totalMessage\"\n        [exportMessage]=\"messages.exportMessage\"\n        [pagerLeftArrowIcon]=\"cssClasses.pagerLeftArrow\"\n        [pagerRightArrowIcon]=\"cssClasses.pagerRightArrow\"\n        [pagerPreviousIcon]=\"cssClasses.pagerPrevious\"\n        [selectedCount]=\"selected.length\"\n        [selectedMessage]=\"!!selectionType && messages.selectedMessage\"\n        [pagerNextIcon]=\"cssClasses.pagerNext\"\n        (page)=\"onFooterPage($event)\"\n        (pageSizeChange)=\"pageSizeChanged($event)\"\n        (export)=\"onExport($event)\">\n      </datatable-footer>\n    </div>\n  ","changeDetection":{"__symbolic":"select","expression":{"__symbolic":"reference","module":"@angular/core","name":"ChangeDetectionStrategy","line":113,"character":19},"member":"OnPush"},"encapsulation":{"__symbolic":"select","expression":{"__symbolic":"reference","module":"@angular/core","name":"ViewEncapsulation","line":114,"character":17},"member":"None"},"styleUrls":["./datatable.component.css"],"host":{"class":"ngx-datatable"}}]}],"members":{"targetMarkerTemplate":[{"__symbolic":"property","decorators":[{"__symbolic":"call","expression":{"__symbolic":"reference","module":"@angular/core","name":"Input","line":125,"character":3}}]}],"rows":[{"__symbolic":"property","decorators":[{"__symbolic":"call","expression":{"__symbolic":"reference","module":"@angular/core","name":"Input","line":130,"character":3}}]}],"groupRowsBy":[{"__symbolic":"property","decorators":[{"__symbolic":"call","expression":{"__symbolic":"reference","module":"@angular/core","name":"Input","line":170,"character":3}}]}],"groupedRows":[{"__symbolic":"property","decorators":[{"__symbolic":"call","expression":{"__symbolic":"reference","module":"@angular/core","name":"Input","line":199,"character":3}}]}],"columns":[{"__symbolic":"property","decorators":[{"__symbolic":"call","expression":{"__symbolic":"reference","module":"@angular/core","name":"Input","line":204,"character":3}}]}],"selected":[{"__symbolic":"property","decorators":[{"__symbolic":"call","expression":{"__symbolic":"reference","module":"@angular/core","name":"Input","line":226,"character":3}}]}],"scrollbarV":[{"__symbolic":"property","decorators":[{"__symbolic":"call","expression":{"__symbolic":"reference","module":"@angular/core","name":"Input","line":231,"character":3}}]}],"scrollbarH":[{"__symbolic":"property","decorators":[{"__symbolic":"call","expression":{"__symbolic":"reference","module":"@angular/core","name":"Input","line":236,"character":3}}]}],"rowHeight":[{"__symbolic":"property","decorators":[{"__symbolic":"call","expression":{"__symbolic":"reference","module":"@angular/core","name":"Input","line":242,"character":3}}]}],"columnMode":[{"__symbolic":"property","decorators":[{"__symbolic":"call","expression":{"__symbolic":"reference","module":"@angular/core","name":"Input","line":248,"character":3}}]}],"headerHeight":[{"__symbolic":"property","decorators":[{"__symbolic":"call","expression":{"__symbolic":"reference","module":"@angular/core","name":"Input","line":254,"character":3}}]}],"footerHeight":[{"__symbolic":"property","decorators":[{"__symbolic":"call","expression":{"__symbolic":"reference","module":"@angular/core","name":"Input","line":260,"character":3}}]}],"externalPaging":[{"__symbolic":"property","decorators":[{"__symbolic":"call","expression":{"__symbolic":"reference","module":"@angular/core","name":"Input","line":266,"character":3}}]}],"externalSorting":[{"__symbolic":"property","decorators":[{"__symbolic":"call","expression":{"__symbolic":"reference","module":"@angular/core","name":"Input","line":272,"character":3}}]}],"limitOptions":[{"__symbolic":"property","decorators":[{"__symbolic":"call","expression":{"__symbolic":"reference","module":"@angular/core","name":"Input","line":274,"character":3}}]}],"limit":[{"__symbolic":"property","decorators":[{"__symbolic":"call","expression":{"__symbolic":"reference","module":"@angular/core","name":"Input","line":297,"character":3}}]}],"count":[{"__symbolic":"property","decorators":[{"__symbolic":"call","expression":{"__symbolic":"reference","module":"@angular/core","name":"Input","line":315,"character":3}}]}],"offset":[{"__symbolic":"property","decorators":[{"__symbolic":"call","expression":{"__symbolic":"reference","module":"@angular/core","name":"Input","line":333,"character":3}}]}],"loadingIndicator":[{"__symbolic":"property","decorators":[{"__symbolic":"call","expression":{"__symbolic":"reference","module":"@angular/core","name":"Input","line":344,"character":3}}]}],"selectionType":[{"__symbolic":"property","decorators":[{"__symbolic":"call","expression":{"__symbolic":"reference","module":"@angular/core","name":"Input","line":358,"character":3}}]}],"reorderable":[{"__symbolic":"property","decorators":[{"__symbolic":"call","expression":{"__symbolic":"reference","module":"@angular/core","name":"Input","line":364,"character":3}}]}],"swapColumns":[{"__symbolic":"property","decorators":[{"__symbolic":"call","expression":{"__symbolic":"reference","module":"@angular/core","name":"Input","line":370,"character":3}}]}],"sortType":[{"__symbolic":"property","decorators":[{"__symbolic":"call","expression":{"__symbolic":"reference","module":"@angular/core","name":"Input","line":375,"character":3}}]}],"sorts":[{"__symbolic":"property","decorators":[{"__symbolic":"call","expression":{"__symbolic":"reference","module":"@angular/core","name":"Input","line":381,"character":3}}]}],"cssClasses":[{"__symbolic":"property","decorators":[{"__symbolic":"call","expression":{"__symbolic":"reference","module":"@angular/core","name":"Input","line":386,"character":3}}]}],"messages":[{"__symbolic":"property","decorators":[{"__symbolic":"call","expression":{"__symbolic":"reference","module":"@angular/core","name":"Input","line":403,"character":3}}]}],"rowIdentity":[{"__symbolic":"property","decorators":[{"__symbolic":"call","expression":{"__symbolic":"reference","module":"@angular/core","name":"Input","line":424,"character":3}}]}],"rowClass":[{"__symbolic":"property","decorators":[{"__symbolic":"call","expression":{"__symbolic":"reference","module":"@angular/core","name":"Input","line":433,"character":3}}]}],"selectCheck":[{"__symbolic":"property","decorators":[{"__symbolic":"call","expression":{"__symbolic":"reference","module":"@angular/core","name":"Input","line":443,"character":3}}]}],"displayCheck":[{"__symbolic":"property","decorators":[{"__symbolic":"call","expression":{"__symbolic":"reference","module":"@angular/core","name":"Input","line":453,"character":3}}]}],"groupExpansionDefault":[{"__symbolic":"property","decorators":[{"__symbolic":"call","expression":{"__symbolic":"reference","module":"@angular/core","name":"Input","line":460,"character":3}}]}],"trackByProp":[{"__symbolic":"property","decorators":[{"__symbolic":"call","expression":{"__symbolic":"reference","module":"@angular/core","name":"Input","line":466,"character":3}}]}],"selectAllRowsOnPage":[{"__symbolic":"property","decorators":[{"__symbolic":"call","expression":{"__symbolic":"reference","module":"@angular/core","name":"Input","line":475,"character":3}}]}],"virtualization":[{"__symbolic":"property","decorators":[{"__symbolic":"call","expression":{"__symbolic":"reference","module":"@angular/core","name":"Input","line":480,"character":3}}]}],"treeFromRelation":[{"__symbolic":"property","decorators":[{"__symbolic":"call","expression":{"__symbolic":"reference","module":"@angular/core","name":"Input","line":485,"character":3}}]}],"treeToRelation":[{"__symbolic":"property","decorators":[{"__symbolic":"call","expression":{"__symbolic":"reference","module":"@angular/core","name":"Input","line":490,"character":3}}]}],"summaryRow":[{"__symbolic":"property","decorators":[{"__symbolic":"call","expression":{"__symbolic":"reference","module":"@angular/core","name":"Input","line":495,"character":3}}]}],"summaryHeight":[{"__symbolic":"property","decorators":[{"__symbolic":"call","expression":{"__symbolic":"reference","module":"@angular/core","name":"Input","line":500,"character":3}}]}],"summaryPosition":[{"__symbolic":"property","decorators":[{"__symbolic":"call","expression":{"__symbolic":"reference","module":"@angular/core","name":"Input","line":505,"character":3}}]}],"exportTitle":[{"__symbolic":"property","decorators":[{"__symbolic":"call","expression":{"__symbolic":"reference","module":"@angular/core","name":"Input","line":507,"character":3}}]}],"exportOptions":[{"__symbolic":"property","decorators":[{"__symbolic":"call","expression":{"__symbolic":"reference","module":"@angular/core","name":"Input","line":509,"character":3}}]}],"scroll":[{"__symbolic":"property","decorators":[{"__symbolic":"call","expression":{"__symbolic":"reference","module":"@angular/core","name":"Output","line":522,"character":3}}]}],"activate":[{"__symbolic":"property","decorators":[{"__symbolic":"call","expression":{"__symbolic":"reference","module":"@angular/core","name":"Output","line":527,"character":3}}]}],"select":[{"__symbolic":"property","decorators":[{"__symbolic":"call","expression":{"__symbolic":"reference","module":"@angular/core","name":"Output","line":532,"character":3}}]}],"sort":[{"__symbolic":"property","decorators":[{"__symbolic":"call","expression":{"__symbolic":"reference","module":"@angular/core","name":"Output","line":537,"character":3}}]}],"page":[{"__symbolic":"property","decorators":[{"__symbolic":"call","expression":{"__symbolic":"reference","module":"@angular/core","name":"Output","line":542,"character":3}}]}],"reorder":[{"__symbolic":"property","decorators":[{"__symbolic":"call","expression":{"__symbolic":"reference","module":"@angular/core","name":"Output","line":547,"character":3}}]}],"resize":[{"__symbolic":"property","decorators":[{"__symbolic":"call","expression":{"__symbolic":"reference","module":"@angular/core","name":"Output","line":552,"character":3}}]}],"tableContextmenu":[{"__symbolic":"property","decorators":[{"__symbolic":"call","expression":{"__symbolic":"reference","module":"@angular/core","name":"Output","line":559,"character":3}}]}],"treeAction":[{"__symbolic":"property","decorators":[{"__symbolic":"call","expression":{"__symbolic":"reference","module":"@angular/core","name":"Output","line":564,"character":3}}]}],"pageSizeChange":[{"__symbolic":"property","decorators":[{"__symbolic":"call","expression":{"__symbolic":"reference","module":"@angular/core","name":"Output","line":566,"character":3}}]}],"isFixedHeader":[{"__symbolic":"property","decorators":[{"__symbolic":"call","expression":{"__symbolic":"reference","module":"@angular/core","name":"HostBinding","line":571,"character":3},"arguments":["class.fixed-header"]}]}],"isFixedRow":[{"__symbolic":"property","decorators":[{"__symbolic":"call","expression":{"__symbolic":"reference","module":"@angular/core","name":"HostBinding","line":582,"character":3},"arguments":["class.fixed-row"]}]}],"isVertScroll":[{"__symbolic":"property","decorators":[{"__symbolic":"call","expression":{"__symbolic":"reference","module":"@angular/core","name":"HostBinding","line":593,"character":3},"arguments":["class.scroll-vertical"]}]}],"isVirtualized":[{"__symbolic":"property","decorators":[{"__symbolic":"call","expression":{"__symbolic":"reference","module":"@angular/core","name":"HostBinding","line":602,"character":3},"arguments":["class.virtualized"]}]}],"isHorScroll":[{"__symbolic":"property","decorators":[{"__symbolic":"call","expression":{"__symbolic":"reference","module":"@angular/core","name":"HostBinding","line":611,"character":3},"arguments":["class.scroll-horz"]}]}],"isSelectable":[{"__symbolic":"property","decorators":[{"__symbolic":"call","expression":{"__symbolic":"reference","module":"@angular/core","name":"HostBinding","line":619,"character":3},"arguments":["class.selectable"]}]}],"isCheckboxSelection":[{"__symbolic":"property","decorators":[{"__symbolic":"call","expression":{"__symbolic":"reference","module":"@angular/core","name":"HostBinding","line":627,"character":3},"arguments":["class.checkbox-selection"]}]}],"isCellSelection":[{"__symbolic":"property","decorators":[{"__symbolic":"call","expression":{"__symbolic":"reference","module":"@angular/core","name":"HostBinding","line":635,"character":3},"arguments":["class.cell-selection"]}]}],"isSingleSelection":[{"__symbolic":"property","decorators":[{"__symbolic":"call","expression":{"__symbolic":"reference","module":"@angular/core","name":"HostBinding","line":643,"character":3},"arguments":["class.single-selection"]}]}],"isMultiSelection":[{"__symbolic":"property","decorators":[{"__symbolic":"call","expression":{"__symbolic":"reference","module":"@angular/core","name":"HostBinding","line":651,"character":3},"arguments":["class.multi-selection"]}]}],"isMultiClickSelection":[{"__symbolic":"property","decorators":[{"__symbolic":"call","expression":{"__symbolic":"reference","module":"@angular/core","name":"HostBinding","line":659,"character":3},"arguments":["class.multi-click-selection"]}]}],"columnTemplates":[{"__symbolic":"property","decorators":[{"__symbolic":"call","expression":{"__symbolic":"reference","module":"@angular/core","name":"ContentChildren","line":668,"character":3},"arguments":[{"__symbolic":"reference","module":"./columns","name":"DataTableColumnDirective","line":668,"character":19}]}]}],"rowDetail":[{"__symbolic":"property","decorators":[{"__symbolic":"call","expression":{"__symbolic":"reference","module":"@angular/core","name":"ContentChild","line":684,"character":3},"arguments":[{"__symbolic":"reference","module":"./row-detail","name":"DatatableRowDetailDirective","line":684,"character":16}]}]}],"groupHeader":[{"__symbolic":"property","decorators":[{"__symbolic":"call","expression":{"__symbolic":"reference","module":"@angular/core","name":"ContentChild","line":690,"character":3},"arguments":[{"__symbolic":"reference","module":"./body/body-group-header.directive","name":"DatatableGroupHeaderDirective","line":690,"character":16}]}]}],"footer":[{"__symbolic":"property","decorators":[{"__symbolic":"call","expression":{"__symbolic":"reference","module":"@angular/core","name":"ContentChild","line":696,"character":3},"arguments":[{"__symbolic":"reference","module":"./footer","name":"DatatableFooterDirective","line":696,"character":16}]}]}],"bodyComponent":[{"__symbolic":"property","decorators":[{"__symbolic":"call","expression":{"__symbolic":"reference","module":"@angular/core","name":"ViewChild","line":703,"character":3},"arguments":[{"__symbolic":"reference","module":"./body","name":"DataTableBodyComponent","line":703,"character":13}]}]}],"headerComponent":[{"__symbolic":"property","decorators":[{"__symbolic":"call","expression":{"__symbolic":"reference","module":"@angular/core","name":"ViewChild","line":714,"character":3},"arguments":[{"__symbolic":"reference","module":"./header","name":"DataTableHeaderComponent","line":714,"character":13}]}]}],"__ctor__":[{"__symbolic":"constructor","parameterDecorators":[[{"__symbolic":"call","expression":{"__symbolic":"reference","module":"@angular/core","name":"SkipSelf","line":753,"character":5}}],[{"__symbolic":"call","expression":{"__symbolic":"reference","module":"@angular/core","name":"SkipSelf","line":754,"character":5}}],null,null,null,null,null,null,null],"parameters":[{"__symbolic":"reference","module":"../services","name":"ScrollbarHelper","line":753,"character":41},{"__symbolic":"reference","module":"../services","name":"DimensionsHelper","line":754,"character":42},{"__symbolic":"reference","module":"@angular/core","name":"ChangeDetectorRef","line":755,"character":16},{"__symbolic":"reference","module":"@angular/core","name":"ElementRef","line":756,"character":13},{"__symbolic":"reference","module":"@angular/core","name":"KeyValueDiffers","line":757,"character":13},{"__symbolic":"reference","module":"../services","name":"ColumnChangesService","line":758,"character":34},{"__symbolic":"reference","module":"../services","name":"ExcelService","line":759,"character":26},{"__symbolic":"reference","module":"@angular/core","name":"ComponentFactoryResolver","line":760,"character":22},{"__symbolic":"reference","module":"@angular/core","name":"Injector","line":761,"character":22}]}],"ngOnInit":[{"__symbolic":"method"}],"ngAfterViewInit":[{"__symbolic":"method"}],"ngAfterContentInit":[{"__symbolic":"method"}],"translateColumns":[{"__symbolic":"method"}],"groupArrayBy":[{"__symbolic":"method"}],"ngDoCheck":[{"__symbolic":"method"}],"recalculate":[{"__symbolic":"method"}],"onWindowResize":[{"__symbolic":"method","decorators":[{"__symbolic":"call","expression":{"__symbolic":"reference","module":"@angular/core","name":"HostListener","line":907,"character":3},"arguments":["window:resize"]},{"__symbolic":"call","expression":{"__symbolic":"reference","module":"../utils","name":"throttleable","line":908,"character":3},"arguments":[5]}]}],"recalculateColumns":[{"__symbolic":"method"}],"recalculateDims":[{"__symbolic":"method"}],"recalculatePages":[{"__symbolic":"method"}],"onBodyPage":[{"__symbolic":"method"}],"onBodyScroll":[{"__symbolic":"method"}],"onFooterPage":[{"__symbolic":"method"}],"calcPageSize":[{"__symbolic":"method"}],"calcRowCount":[{"__symbolic":"method"}],"onColumnContextmenu":[{"__symbolic":"method"}],"onRowContextmenu":[{"__symbolic":"method"}],"onColumnResize":[{"__symbolic":"method"}],"onColumnReorder":[{"__symbolic":"method"}],"onColumnSort":[{"__symbolic":"method"}],"onHeaderSelect":[{"__symbolic":"method"}],"onBodySelect":[{"__symbolic":"method"}],"onTreeAction":[{"__symbolic":"method"}],"pageSizeChanged":[{"__symbolic":"method"}],"onExport":[{"__symbolic":"method"}],"getDataRowsForExport":[{"__symbolic":"method"}],"getRenderedTemplateText":[{"__symbolic":"method"}],"getNestedPropertyValue":[{"__symbolic":"method"}],"ngOnDestroy":[{"__symbolic":"method"}],"listenForColumnInputChanges":[{"__symbolic":"method"}],"sortInternalRows":[{"__symbolic":"method"}]}}}}]